xmanage/__init__.py
xmanage/utils/__init__.py
xmanage/utils/attribute.py
xmanage/utils/systemd/__init__.py
xmanage/utils/systemd/path.py
xmanage/utils/systemd/service.py
xmanage/utils/systemd/unit.py
xmanage/xsystem/__init__.py
xmanage/xsystem/path.py
xmanage.utils-0.4.dist-info/LICENSE
xmanage.utils-0.4.dist-info/METADATA
xmanage.utils-0.4.dist-info/WHEEL
xmanage.utils-0.4.dist-info/entry_points.txt
xmanage.utils-0.4.dist-info/top_level.txt
xmanage.utils-0.4.dist-info/zip-safe
xmanage.utils-0.4.dist-info/RECORD
